[
    {
    "title" : "Pensamientos de la representante de Daibic Corporation, Noro",
    "content" : "¿Por qué creaste una escuela de programación? ¡Te contaré sobre la experiencia original!",
    "url" : "https://www.youtube.com/embed/Ho1NLq7fpJQ"
    },
    {
      "title" : "DEMODAY 3rd",
      "content" : "DEMODAY 3rd Le enviaremos un video resumen desde la sala de seminarios de Leverages Co., Ltd. en el lugar.",
      "url" : "https://www.youtube.com/embed/S9qp7QMCabM"
    },
    {
      "title" : "DIC Studio",
      "content" : "【DIC Studio】Vol.10 aclama el entrevistador",
      "url" : "https://www.youtube.com/embed/q1AvJPTrfM4"
    }
  ]
  